streamlit_nies/__init__.py
streamlit_nies/heat_map_consistent_altair.py
streamlit_nies/polar_bar_plotly.py
streamlit_nies/transformations.py
streamlit_nies-0.1.1.dist-info/LICENSE
streamlit_nies-0.1.1.dist-info/WHEEL
streamlit_nies-0.1.1.dist-info/METADATA
streamlit_nies-0.1.1.dist-info/RECORD
